<annotation>
	<folder>2020.03.19</folder>
	<filename>202003081545.bmp</filename>
	<path>C:\Users\hjy\Desktop\2020.03.19\202003081545.bmp</path>
	<source>
		<database>Unknown</database>
	</source>
	<size>
		<width>512</width>
		<height>512</height>
		<depth>1</depth>
	</size>
	<segmented>0</segmented>
	<object>
		<name>zongxiangliewen</name>
		<pose>Unspecified</pose>
		<truncated>0</truncated>
		<difficult>0</difficult>
		<bndbox>
			<xmin>379</xmin>
			<ymin>76</ymin>
			<xmax>400</xmax>
			<ymax>273</ymax>
		</bndbox>
	</object>
	<object>
		<name>zongxiangliewen</name>
		<pose>Unspecified</pose>
		<truncated>0</truncated>
		<difficult>0</difficult>
		<bndbox>
			<xmin>365</xmin>
			<ymin>344</ymin>
			<xmax>395</xmax>
			<ymax>507</ymax>
		</bndbox>
	</object>
</annotation>
